setup.py
my_gaubi_distributions/Binomialdistribution.py
my_gaubi_distributions/Gaussiandistribution.py
my_gaubi_distributions/Generaldistribution.py
my_gaubi_distributions/__init__.py
my_gaubi_distributions.egg-info/PKG-INFO
my_gaubi_distributions.egg-info/SOURCES.txt
my_gaubi_distributions.egg-info/dependency_links.txt
my_gaubi_distributions.egg-info/not-zip-safe
my_gaubi_distributions.egg-info/top_level.txt